zmp_zcp_toolkit/__init__.py
zmp_zcp_toolkit/models/mixed_spec.py
zmp_zcp_toolkit/models/operation.py
zmp_zcp_toolkit/openapi/fastapi_models.py
zmp_zcp_toolkit/openapi/openapi_helper.py
zmp_zcp_toolkit/openapi/zmpapi_models.py
zmp_zcp_toolkit/toolkits/toolkit.py
zmp_zcp_toolkit/tools/tool.py
zmp_zcp_toolkit/wrapper/api_wrapper.py
zmp_zcp_toolkit-0.2.12.dist-info/LICENSE
zmp_zcp_toolkit-0.2.12.dist-info/METADATA
zmp_zcp_toolkit-0.2.12.dist-info/WHEEL
zmp_zcp_toolkit-0.2.12.dist-info/RECORD
