Metadata-Version: 2.3
Name: zmp-zcp-toolkit
Version: 0.2.12
Summary: 
License: MIT
Author: Kilsoo Kang
Author-email: kilsoo75@gmail.com
Requires-Python: >=3.11,<4.0
Classifier: License :: OSI Approved :: MIT License
Classifier: Programming Language :: Python :: 3
Classifier: Programming Language :: Python :: 3.11
Classifier: Programming Language :: Python :: 3.12
Classifier: Programming Language :: Python :: 3.13
Requires-Dist: colorlog (>=6.9.0,<7.0.0)
Requires-Dist: langchain (>=0.3.18,<0.4.0)
Requires-Dist: langchain-core (>=0.3.35,<0.4.0)
Requires-Dist: python-dotenv (>=1.0.1,<2.0.0)
Project-URL: Homepage, https://github.com/cloudz-mp
Project-URL: Repository, https://github.com/cloudz-mp/zmp-zcp-toolkit
